pratice/first_counter/first_counter_buggy_var.v
//-----------------------------------------
//Design name: first_counter
//File Name: first_counter.v
//Function: This is a 4-bit up-counter with
//Synchronous active high reset and 
//with active high enable signal
//------------------------------------------
module first_counter(
    clk,
    reset,
    enable,
    counter_out
);// End of port list
//----------------Input Ports---------------
input clk;
input reset;
input enable;
//----------------Output Ports--------------
output[3:0] counter_out;
//----------------Input ports Data Type-----
//By rule all the input ports should be wires
wire clk;
wire reset;
wire enable;
//----------------Output ports data type----
//Output port can be a storage element(reg) or a wire
reg[3:0] counter_out;

//---------------Code starts here-----------
always@(posedge clk)
begin: COUNTER //block name
    //At every rising edge of clock we check if reset is active
    //If active, we load the counter output with 4'b0000
    if(clk==1'b1) begin
        counter_out <= #1 4'b0000;
    end
    //If enable is active, we increment the counter
    else if(enable == 1'b1) begin
        counter_out <= #1 counter_out + 1;
    end
end // End of block COUNTER

endmodule // End of module counter

practice/first_counter/first_counter_tb.v
// Self-checking testbench for first_counter.v
// DUT is instantiated in tb, tb will contain a clock generator, reset
// generator, enable logic generator, compare logic.


// step1: create a dummy template that declares inputs to DUT as reg,
// declare outputs of DUT as wire. Note there is no port list for test
// bench.
module first_counter_tb;
reg clk, reset, enable;
wire[3:0] counter_out;



first_counter U0(
    .clk (clk),
    .reset (reset),
    .enable (enable),
    .counter_out (counter_out)
);

// step2: add clock generator logic. Before this we need to drive all
// inputs of DUT to some known state.
initial begin // initial block only executes once 
    clk = 0;
    reset = 0;
    enable = 0;
end

always
    #5 clk = !clk;

initial begin
    $dumpfile ("first_counter.vcd"); //dumpfile is for specifying the file that simulator will use to store the waveform
    $dumpvars; // dumpvars instructs the Verilog compiler to start dumping all signals to the dumpfile.
end

initial begin
    $display("\t\ttime,\tclk,\treset,\tenable,\tcount_out");
    $monitor("%d, \t%b, \t%b, \t%b, \t%d", $time, clk, reset, enable, counter_out);
end



event reset_trigger;
event reset_done_trigger;
event terminate_sim;


initial begin
    forever begin
        @(reset_trigger);
        @(negedge clk);
        reset = 1;
        @(negedge clk);
        reset = 0;
        -> reset_done_trigger;
    end
end

initial begin
    @(terminate_sim);
    #5 $finish;
end

/*
// Test Case 1: Assert/Deassert reset
// trigger the reset_trigger event after 10 time units
initial begin: TEST_CASE_1
    #10 -> reset_trigger;
end
*/



// Test Case 2: Assert/Deassert enable after reset is applied
// trigger the reset logic and wait for it to complete. Then drive
// enable to 1
/*
reg temp_event1;

initial begin
    temp_event1 = 0;
       #10;
    temp_event1 = 1;
end
*/

/*
initial begin: TEST_CASE_2
    #10 -> reset_trigger;
   // @(posedge temp_event1);
    
    @(reset_done_trigger);
    @(negedge clk);
    enable = 1;
    repeat (10) begin
        @(negedge clk);
    end
    enable = 0;
    #5 -> terminate_sim;
end
*/

// Test Case 3: Assert/Deassert enable and reset randomly
initial begin: TEST_CASE_3
    #10 -> reset_trigger;
    @(reset_done_trigger);
    fork
        repeat (10) begin
            @(negedge clk);
            enable = $random;
        end
        repeat (10) begin
            @(negedge clk);
            reset = $random;
        end
    join
end


// Adding Compare logic
reg [3:0] count_compare;

always @ (posedge clk)
    if (reset==1'b1) begin
        count_compare<=0;
    end 
    else if (enable == 1'b1) begin
        count_compare <= count_compare + 1;
    end


// Adding checking logic: at any given point, keep checking the expected
// value with the actual value. Whenever there is an error, print out
// the expected and actual value, also terminate the simulation by
// trigering the event "terminate_sim".
always@(posedge clk)
    if (count_compare != counter_out) begin
        $display ("DUT ERROR at time %d", $time);
        $display ("Expected Value %d, Got Value %d", count_compare, counter_out);
        #5 -> terminate_sim;
    end


initial begin
    #500
    
    //@(negedge clk)
    //#5 $display ("Simulation SUCCESS!");
     -> terminate_sim; // terminate simulation after 100 time units.

end

endmodule

pratice/first_counter/first_counter.vcd
$date
	Thu May 14 17:44:52 2020
$end

$version
	Synopsys VCS version N-2017.12-SP2-1_Full64
$end

$timescale
	1s
$end

$comment Csum: 1 12991fb738b392f1 $end


$scope module $unit $end
$upscope $end


$scope module first_counter_tb $end
$var reg 1 ! clk $end
$var reg 1 " reset $end
$var reg 1 # enable $end
$var wire 4 $ counter_out [3:0] $end
$var reg 4 % count_compare [3:0] $end
$var event 1 & reset_trigger $end
$var event 1 ' reset_done_trigger $end
$var event 1 ( terminate_sim $end

$scope begin TEST_CASE_3 $end

$scope fork unnamed$$_vcs_0 $end

$scope begin unnamed$$_vcs_1 $end
$upscope $end


$scope begin unnamed$$_vcs_2 $end
$upscope $end

$upscope $end

$upscope $end


$scope module U0 $end
$var wire 1 ! clk $end
$var wire 1 " reset $end
$var wire 1 # enable $end
$var reg 4 $ counter_out [3:0] $end

$scope begin COUNTER $end
$upscope $end

$upscope $end

$upscope $end

$enddefinitions $end

#0
$dumpvars
0!
0#
0"
x'
x&
x(
bxxxx $
bxxxx %
$end
#5
1!
#10
x&
0!
#15
1!
#20
0!
1"
#25
1!
b0000 %
#26
b0000 $
#30
0!
x'
0"
#35
1!
#40
0!
1"
#45
1!
#50
0!
1#
#55
1!
#60
0!
#65
1!
#70
0!
0"
#75
1!
b0001 %
#76
b0001 $
#80
0!
1"
#85
1!
b0000 %
#86
b0000 $
#90
0!
0#
#95
1!
#100
0!
1#
0"
#105
1!
b0001 %
#106
b0001 $
#110
0!
#115
1!
b0010 %
#116
b0010 $
#120
0!
#125
1!
b0011 %
#126
b0011 $
#130
0!
1"
#135
1!
b0000 %
#136
b0000 $
